geekhours/__init__.py
geekhours/command.py
geekhours/database.py
geekhours/util.py
geekhours/test/__init__.py
geekhours/test/test_command.py
geekhours/test/test_database.py
geekhours-0.0.1.data/scripts/geekhours
geekhours-0.0.1.dist-info/LICENSE
geekhours-0.0.1.dist-info/METADATA
geekhours-0.0.1.dist-info/WHEEL
geekhours-0.0.1.dist-info/top_level.txt
geekhours-0.0.1.dist-info/RECORD
