Metadata-Version: 2.1
Name: geekhours
Version: 0.0.1
Summary: Study time management tool
Home-page: https://github.com/YukieK/GeekHours.git
Author: Yukie Kato
Author-email: yukie.kato.28@gmail.com
Maintainer: Mitz Amano
License: MIT
Platform: Linux
Classifier: Development Status :: 2 - Pre-Alpha
Classifier: License :: OSI Approved :: MIT License
Classifier: Programming Language :: Python :: 3.5
Classifier: Environment :: Console
Classifier: Operating System :: POSIX :: Linux
Requires-Python: ~=3.5
